factbase/__init__.py
factbase-0.0.4.dist-info/METADATA
factbase-0.0.4.dist-info/WHEEL
factbase-0.0.4.dist-info/top_level.txt
factbase-0.0.4.dist-info/RECORD
