Metadata-Version: 2.1
Name: factbase
Version: 0.0.4
Summary: The FactBase Python SDK
Home-page: https://factbase.io
Author: Tobias Herrmann
Author-email: tobias@cleip.com
License: UNKNOWN
Project-URL: Source, https://github.com/FactBaseIO/factbase-python-sdk
Platform: UNKNOWN
Classifier: Development Status :: 1 - Planning
Classifier: Intended Audience :: Developers
Classifier: License :: OSI Approved :: MIT License
Classifier: Programming Language :: Python :: 3
Classifier: Programming Language :: Python :: 3.6
Classifier: Programming Language :: Python :: 3.7
Classifier: Programming Language :: Python :: 3.8
Classifier: Programming Language :: Python :: 3.9
Requires-Python: >=3.6
